{
	"type": "recipe",
	"work_units": 1,
	"recipe_name": "i18n(craftmod:jobs.blacksmith.recipes.ore.tin_recipe.recipe_name)",
	"description": "i18n(craftmod:jobs.blacksmith.recipes.ore.tin_recipe.description)",
	"flavor": "",
	"portrait": "/craftmod/entities/tin/tin.png",
	"workshop": "stonehearth:blacksmith:forge",
	"level_requirement": 0,
	"ingredients": [{
         "uri": "stonehearth:resources:tin:ore",
         "count": 1
      }],
	"produces": [
		{
		"item": "stonehearth:resources:tin:ore"
		},
		{
		"item": "stonehearth:resources:tin:ore"
		},
		{
		"item": "stonehearth:resources:tin:ore"
		},
		{
		"item": "stonehearth:resources:tin:ore"
		},
		{
		"item": "stonehearth:resources:tin:ore"
		}
	]
}